LICENSE
README.md
setup.py
tap_taboola/__init__.py
tap_taboola/schemas.py
tap_taboola.egg-info/PKG-INFO
tap_taboola.egg-info/SOURCES.txt
tap_taboola.egg-info/dependency_links.txt
tap_taboola.egg-info/entry_points.txt
tap_taboola.egg-info/requires.txt
tap_taboola.egg-info/top_level.txt